Metadata-Version: 2.1
Name: Election-Vote
Version: 0.0.1
Summary: Displays the button on the Front endto vote for the students 
Home-page: 
Author: Yamini x23166401@student.ncirl.ie
Author-email: x23166401@student.ncirl.ie
License: MIT
Keywords: Election-Vote
Classifier: Development Status :: 5 - Production/Stable
Classifier: Intended Audience :: Education
Classifier: Operating System :: Microsoft :: Windows :: Windows 10
Classifier: License :: OSI Approved :: MIT License
Classifier: Programming Language :: Python :: 3
License-File: LICENCE.txt
